[
  {
    "name": "AFC",
    "worldCupSpots": 8,
    "teams": [
      {
        "name": "Japão",
        "continent": "AFC",
        "latitude": 35.68,
        "longitude": 139.69,
        "power": 7.0,
        "distance": 1975
      },
      {
        "name": "Irã",
        "continent": "AFC",
        "latitude": 32.43,
        "longitude": 53.69,
        "power": 6.8,
        "distance": 1460
      },
      {
        "name": "Austrália",
        "continent": "AFC",
        "latitude": -33.21,
        "longitude": 140.73,
        "power": 6.6,
        "distance": 2250
      },
      {
        "name": "Coréia do Sul",
        "continent": "AFC",
        "latitude": 35.91,
        "longitude": 127.77,
        "power": 6.4,
        "distance": 850
      },
      {
        "name": "Catar",
        "continent": "AFC",
        "latitude": 25.35,
        "longitude": 51.18,
        "power": 6.2,
        "distance": 65
      },
      {
        "name": "Arábia Saudita",
        "continent": "AFC",
        "latitude": 24.47,
        "longitude": 39.83,
        "power": 6.0,
        "distance": 1175
      },
      {
        "name": "Iraque",
        "continent": "AFC",
        "latitude": 33.22,
        "longitude": 43.68,
        "power": 5.4,
        "distance": 725
      },
      {
        "name": "Emirados Árabes Unidos",
        "continent": "AFC",
        "latitude": 23.71,
        "longitude": 43.09,
        "power": 5.2,
        "distance": 325
      },
      {
        "name": "Jordânia",
        "continent": "AFC",
        "latitude": 30.59,
        "longitude": 36.28,
        "power": 5.2,
        "distance": 275
      },
      {
        "name": "China",
        "continent": "AFC",
        "latitude": 31.18,
        "longitude": 116.48,
        "power": 5.0,
        "distance": 2525
      },
      {
        "name": "Omã",
        "continent": "AFC",
        "latitude": 21.51,
        "longitude": 55.92,
        "power": 5.0,
        "distance": 560
      }
    ]
  },
  {
    "name": "CAF",
    "worldCupSpots": 8,
    "teams": [
      {
        "name": "Marrocos",
        "continent": "CAF",
        "latitude": 33.81,
        "longitude": -6.65,
        "power": 7.2,
        "distance": 850
      },
      {
        "name": "Senegal",
        "continent": "CAF",
        "latitude": 14.5,
        "longitude": -14.45,
        "power": 6.8,
        "distance": 425
      },
      {
        "name": "Nigéria",
        "continent": "CAF",
        "latitude": 9.08,
        "longitude": 8.68,
        "power": 6.6,
        "distance": 920
      },
      {
        "name": "Costa do Marfim",
        "continent": "CAF",
        "latitude": 7.54,
        "longitude": -5.55,
        "power": 6.4,
        "distance": 550
      },
      {
        "name": "Egito",
        "continent": "CAF",
        "latitude": 30.53,
        "longitude": 31.18,
        "power": 6.2,
        "distance": 1000
      },
      {
        "name": "Argélia",
        "continent": "CAF",
        "latitude": 36.25,
        "longitude": 4.59,
        "power": 6.0,
        "distance": 1450
      },
      {
        "name": "Camarões",
        "continent": "CAF",
        "latitude": 7.37,
        "longitude": 12.35,
        "power": 5.8,
        "distance": 575
      },
      {
        "name": "Tunísia",
        "continent": "CAF",
        "latitude": 33.89,
        "longitude": 9.53,
        "power": 5.6,
        "distance": 420
      },
      {
        "name": "Mali",
        "continent": "CAF",
        "latitude": 12.86,
        "longitude": -5.91,
        "power": 5.2,
        "distance": 750
      },
      {
        "name": "Gana",
        "continent": "CAF",
        "latitude": 7.95,
        "longitude": -1.02,
        "power": 5.0,
        "distance": 425
      },
      {
        "name": "Guiné",
        "continent": "CAF",
        "latitude": 9.81,
        "longitude": -11.39,
        "power": 5.0,
        "distance": 800
      }
    ]
  },
  {
    "name": "CONCACAF",
    "worldCupSpots": 4,
    "teams": [
      {
        "name": "Estados Unidos",
        "continent": "CONCACAF",
        "latitude": 35.97,
        "longitude": -97.46,
        "power": 7.2,
        "distance": 2825
      },
      {
        "name": "México",
        "continent": "CONCACAF",
        "latitude": 23.63,
        "longitude": -102.55,
        "power": 7.0,
        "distance": 1625
      },
      {
        "name": "Panamá",
        "continent": "CONCACAF",
        "latitude": 8.54,
        "longitude": -80.78,
        "power": 5.8,
        "distance": 225
      },
      {
        "name": "Canadá",
        "continent": "CONCACAF",
        "latitude": 46.98,
        "longitude": -93.16,
        "power": 5.6,
        "distance": 2150
      },
      {
        "name": "Costa Rica",
        "continent": "CONCACAF",
        "latitude": 9.75,
        "longitude": -83.75,
        "power": 5.4,
        "distance": 150
      },
      {
        "name": "Jamaica",
        "continent": "CONCACAF",
        "latitude": 18.11,
        "longitude": -77.3,
        "power": 5.0,
        "distance": 175
      }
    ]
  },
  {
    "name": "CONMEBOL",
    "worldCupSpots": 8,
    "teams": [
      {
        "name": "Brasil",
        "continent": "CONMEBOL",
        "latitude": -15.78,
        "longitude": -42.95,
        "power": 9.0,
        "distance": 2425
      },
      {
        "name": "Argentina",
        "continent": "CONMEBOL",
        "latitude": -32.89,
        "longitude": -64.18,
        "power": 8.8,
        "distance": 2025
      },
      {
        "name": "Uruguai",
        "continent": "CONMEBOL",
        "latitude": -32.52,
        "longitude": -55.77,
        "power": 7.6,
        "distance": 250
      },
      {
        "name": "Colômbia",
        "continent": "CONMEBOL",
        "latitude": 4.57,
        "longitude": -74.3,
        "power": 7.0,
        "distance": 1375
      },
      {
        "name": "Equador",
        "continent": "CONMEBOL",
        "latitude": -1.83,
        "longitude": -78.18,
        "power": 6.6,
        "distance": 650
      },
      {
        "name": "Peru",
        "continent": "CONMEBOL",
        "latitude": -9.19,
        "longitude": -75.02,
        "power": 6.4,
        "distance": 1225
      },
      {
        "name": "Chile",
        "continent": "CONMEBOL",
        "latitude": -35.68,
        "longitude": -71.54,
        "power": 5.8,
        "distance": 1375
      },
      {
        "name": "Bolívia",
        "continent": "CONMEBOL",
        "latitude": -16.29,
        "longitude": -63.59,
        "power": 5.4,
        "distance": 1200
      },
      {
        "name": "Paraguai",
        "continent": "CONMEBOL",
        "latitude": -23.44,
        "longitude": -58.44,
        "power": 5.0,
        "distance": 575
      },
      {
        "name": "Venezuela",
        "continent": "CONMEBOL",
        "latitude": 6.42,
        "longitude": -66.59,
        "power": 5.0,
        "distance": 1100
      }
    ]
  },
  {
    "name": "UEFA",
    "worldCupSpots": 16,
    "teams": [
      {
        "name": "França",
        "continent": "UEFA",
        "latitude": 46.6,
        "longitude": 1.89,
        "power": 9.6,
        "distance": 825
      },
      {
        "name": "Inglaterra",
        "continent": "UEFA",
        "latitude": 52.36,
        "longitude": -1.17,
        "power": 9.4,
        "distance": 550
      },
      {
        "name": "Espanha",
        "continent": "UEFA",
        "latitude": 40.46,
        "longitude": -3.75,
        "power": 9.2,
        "distance": 750
      },
      {
        "name": "Países Baixos",
        "continent": "UEFA",
        "latitude": 52.13,
        "longitude": 5.29,
        "power": 8.6,
        "distance": 200
      },
      {
        "name": "Alemanha",
        "continent": "UEFA",
        "latitude": 51.17,
        "longitude": 10.45,
        "power": 8.4,
        "distance": 625
      },
      {
        "name": "Itália",
        "continent": "UEFA",
        "latitude": 41.89,
        "longitude": 12.48,
        "power": 8.2,
        "distance": 800
      },
      {
        "name": "Croácia",
        "continent": "UEFA",
        "latitude": 45.1,
        "longitude": 15.2,
        "power": 8.0,
        "distance": 300
      },
      {
        "name": "Portugal",
        "continent": "UEFA",
        "latitude": 39.4,
        "longitude": -8.22,
        "power": 7.8,
        "distance": 375
      },
      {
        "name": "Bélgica",
        "continent": "UEFA",
        "latitude": 50.85,
        "longitude": 4.35,
        "power": 7.4,
        "distance": 150
      },
      {
        "name": "Dinamarca",
        "continent": "UEFA",
        "latitude": 56.26,
        "longitude": 9.5,
        "power": 7.2,
        "distance": 325
      },
      {
        "name": "Suíça",
        "continent": "UEFA",
        "latitude": 46.81,
        "longitude": 8.23,
        "power": 7.2,
        "distance": 300
      },
      {
        "name": "Áustria",
        "continent": "UEFA",
        "latitude": 47.52,
        "longitude": 14.55,
        "power": 7.0,
        "distance": 325
      },
      {
        "name": "Hungria",
        "continent": "UEFA",
        "latitude": 47.16,
        "longitude": 19.5,
        "power": 6.8,
        "distance": 475
      },
      {
        "name": "Suécia",
        "continent": "UEFA",
        "latitude": 58.42,
        "longitude": 15.44,
        "power": 6.8,
        "distance": 575
      },
      {
        "name": "Ucrânia",
        "continent": "UEFA",
        "latitude": 48.38,
        "longitude": 31.17,
        "power": 6.6,
        "distance": 925
      },
      {
        "name": "Sérvia",
        "continent": "UEFA",
        "latitude": 44.02,
        "longitude": 21.0,
        "power": 6.4,
        "distance": 475
      },
      {
        "name": "País de Gales",
        "continent": "UEFA",
        "latitude": 52.3,
        "longitude": -3.9,
        "power": 6.2,
        "distance": 300
      },
      {
        "name": "Polônia",
        "continent": "UEFA",
        "latitude": 51.92,
        "longitude": 19.14,
        "power": 6.2,
        "distance": 625
      },
      {
        "name": "República Tcheca",
        "continent": "UEFA",
        "latitude": 49.82,
        "longitude": 15.47,
        "power": 6.0,
        "distance": 350
      },
      {
        "name": "Turquia",
        "continent": "UEFA",
        "latitude": 39.31,
        "longitude": 30.67,
        "power": 6.0,
        "distance": 1050
      },
      {
        "name": "Noruega",
        "continent": "UEFA",
        "latitude": 60.49,
        "longitude": 8.48,
        "power": 5.8,
        "distance": 500
      },
      {
        "name": "Escócia",
        "continent": "UEFA",
        "latitude": 56.49,
        "longitude": -4.2,
        "power": 5.6,
        "distance": 325
      },
      {
        "name": "Romênia",
        "continent": "UEFA",
        "latitude": 45.94,
        "longitude": 24.97,
        "power": 5.6,
        "distance": 650
      },
      {
        "name": "Grécia",
        "continent": "UEFA",
        "latitude": 38.24,
        "longitude": 22.94,
        "power": 5.4,
        "distance": 450
      },
      {
        "name": "Eslováquia",
        "continent": "UEFA",
        "latitude": 48.67,
        "longitude": 19.7,
        "power": 5.2,
        "distance": 275
      },
      {
        "name": "Eslovênia",
        "continent": "UEFA",
        "latitude": 46.15,
        "longitude": 14.99,
        "power": 5.0,
        "distance": 175
      }
    ]
  }
]
